linux/__init__.py
linux/linux_vm.py
linux/webserver.py
linux_vm-1.0.dist-info/METADATA
linux_vm-1.0.dist-info/WHEEL
linux_vm-1.0.dist-info/entry_points.txt
linux_vm-1.0.dist-info/top_level.txt
linux_vm-1.0.dist-info/RECORD
