Metadata-Version: 2.1
Name: linux_vm
Version: 1.0
Summary: A package to manage a Docker-based Linux VM and start a web server.
Home-page: https://github.com/Tirthaboss/linux_vm
Author: Souporno Chakraborty
Author-email: shrabanichakraborty83@gmail.com
Requires-Dist: docker
